Workbook
Name SegmentaciónDeDatos_Jerarquía_de_fechas: #N/A
Name SegmentaciónDeDatos_Tipo_de_producto: #N/A
Name SegmentaciónDeDatos_Zona: #N/A

Sheet Hechos
A1: ID Cliente | B1: ID PRODUCTO | C1: Prioridad | D1: Fecha pedido | E1: ID Pedido | F1: Fecha envío | G1: Unidades | H1: Precio Unitario | I1: Coste unitario | J1: Importe venta total | K1: Importe Coste total
A2: C2421 | B2: PRO 1 | C2: Crítica | D2: 44116 | E2: 242113196 | F2: 44165 | G2: 5530 | H2: 152.58 | I2: 97.44 | J2: 843767.4 | K2: 538843.2
A3: C1908 | B3: PRO 2 | C3: Alta | D3: 43856 | E3: 190800607 | F3: 43858 | G3: 994 | H3: 421.89 | I3: 364.69 | J3: 419358.66 | K3: 362501.86
A4: C7652 | B4: PRO 3 | C4: Crítica | D4: 44144 | E4: 765228068 | F4: 44156 | G4: 6845 | H4: 205.7 | I4: 117.11 | J4: 1408016.5 | K4: 801617.95
A5: C2326 | B5: PRO 4 | C5: Baja | D5: 44429 | E5: 232631909 | F5: 44471 | G5: 9806 | H5: 9.33 | I5: 6.92 | J5: 91489.98 | K5: 67857.52
A6: C5305 | B6: PRO 5 | C6: Media | D6: 44834 | E6: 530560958 | F6: 44877 | G6: 3633 | H6: 255.28 | I6: 159.42 | J6: 927432.24 | K6: 579172.86
A7: C5168 | B7: PRO 6 | C7: Baja | D7: 44582 | E7: 516876542 | F7: 44613 | G7: 4110 | H7: 47.45 | I7: 31.79 | J7: 195019.5 | K7: 130656.9
A8: C9197 | B8: PRO 1 | C8: Media | D8: 44609 | E8: 919752490 | F8: 44619 | G8: 4056 | H8: 152.58 | I8: 97.44 | J8: 618864.48 | K8: 395216.64
A9: C2876 | B9: PRO 7 | C9: Media | D9: 43911 | E9: 287675130 | F9: 43958 | G9: 8319 | H9: 437.2 | I9: 263.33 | J9: 3637066.8 | K9: 2190642.3
A10: C8394 | B10: PRO 8 | C10: Crítica | D10: 44240 | E10: 839443290 | F10: 44287 | G10: 8779 | H10: 81.73 | I10: 56.67 | J10: 717507.67 | K10: 497505.93
A11: C8141 | B11: PRO 9 | C11: Media | D11: 44362 | E11: 814168298 | F11: 44389 | G11: 9347 | H11: 651.21 | I11: 524.96 | J11: 6086859.9 | K11: 4906801.1
A12: C3212 | B12: PRO 7 | C12: Alta | D12: 44757 | E12: 321273982 | F12: 44803 | G12: 966 | H12: 437.2 | I12: 263.33 | J12: 422335.2 | K12: 254376.78
A13: C8904 | B13: PRO 1 | C13: Crítica | D13: 43964 | E13: 890496671 | F13: 43987 | G13: 6609 | H13: 152.58 | I13: 97.44 | J13: 1008401.2 | K13: 643980.96
... A1001: C2793 | B1001: PRO 11 | C1001: Crítica | D1001: 44583 | E1001: 279311788 | F1001: 44593 | G1001: 3420 | H1001: 109.28 | I1001: 35.84 | J1001: 373737.6 | K1001: 122572.8

Sheet Dim_Clientes
A1: ID Cliente | B1: Zona | C1: País
A2: C1008 | B2: Asia | C2: Tajikistan
A3: C1061 | B3: Europa | C3: Czech Republic
A4: C1062 | B4: Centroamérica y Caribe | C4: Cuba
A5: C1069 | B5: África | C5: Oman
A6: C1089 | B6: África | C6: Cape Verde
A7: C1112 | B7: Asia | C7: Mongolia
A8: C1114 | B8: Asia | C8: Laos
A9: C1116 | B9: Europa | C9: Bosnia and Herzegovina
A10: C1118 | B10: Australia y Oceanía | C10: East Timor
A11: C1123 | B11: África | C11: Togo
A12: C1124 | B12: Europa | C12: Norway
... A952: C9987 | B952: Asia | C952: Malaysia

Sheet Dim_Productos
A1: ID | B1: Tipo de producto
A2: PRO 1 | B2: Snacks
A3: PRO 2 | B3: Cárnicos
A4: PRO 3 | B4: Cereales
A5: PRO 4 | B5: Frutas
A6: PRO 5 | B6: Alimento infantil
A7: PRO 6 | B7: Bebida
A8: PRO 7 | B8: Cosméticos
A9: PRO 8 | B9: Cuidado personal
A10: PRO 9 | B10: Material de oficina
A11: PRO 10 | B11: Verduras
A12: PRO 11 | B12: Ropa
A13: PRO 12 | B13: Doméstico

Sheet Tablas_Dinamicas
A1: LA AMALFITANA S.A.
A5: VENTAS ANUALES | J5: RESUMEN GENERAL | O5: TEXTO TARJETAS KPI
A7: Año | B7: Importe | J7: Total Venta | K7: Coste Total | L7: Margen de Ventas | O7: KPI | P7: Texto | Q7: Meta | R7: ¿Cumple? | S7: Indicador
A8: 2020 | B8: 4.3729163e+08 | J8: 1.2891019e+09 | K8: 9.0707652e+08 | L8: 0.29635003 | O8: Venta total | P8: =TEXT(J8,"$ #.##0.. ""M""") -> $ 1.289 M | Q8: 1500000000 | R8: =J8>=Q8 -> FALSE | S8: =IF(R8,"▲ Sobre la meta (","▼ Bajo la meta (")&TEXT(Q8,"$ #.##0.. ""M""")&")" -> ▼ Bajo la meta ($ 1.500 M)
A9: 2021 | B9: 4.832354e+08 | O9: Coste total | P9: =TEXT(K8,"$ #.##0.. ""M""") -> $ 907 M | Q9: 1000000000 | R9: =K8<=Q9 -> TRUE | S9: =IF(R9,"▼ Dentro del máximo (","▲ Sobre el máximo (")&TEXT(Q9,"$ #.##0.. ""M""")&")" -> ▼ Dentro del máximo ($ 1.000 M)
A10: 2022 | B10: 3.6857487e+08 | J10: Ventas | K10: =J8 -> 1.2891019e+09 | O10: Margen de ventas | P10: =TEXT(L8,"0,0%") -> 29,6% | Q10: 0.35 | R10: =L8>=Q10 -> FALSE | S10: =IF(R10,"▲ Sobre la meta (","▼ Bajo la meta (")&TEXT(Q10,"0,0%")&")" -> ▼ Bajo la meta (35,0%)
A11: Total Ventas | B11: 1.2891019e+09 | J11: Costos | K11: =-K8 -> -9.0707652e+08
J12: Ganancia | K12: =K10+K11 -> 3.8202538e+08
A14: MARGEN POR PRODUCTO | F14: VENTAS POR ZONA
A16: Producto | B16: Margen de Ventas | F16: Región | G16: Total Venta
A17: Cárnicos | B17: 0.13558036 | F17: África | G17: 5.0551261e+08
A18: Material de oficina | B18: 0.19386987 | F18: Europa | G18: 2.8622126e+08
A19: Doméstico | B19: 0.24799856 | F19: Asia | G19: 1.9859234e+08
A20: Frutas | B20: 0.25830654 | F20: Centroamérica y Caribe | G20: 1.4560825e+08
A21: Cuidado personal | B21: 0.30661936 | F21: Australia y Oceanía | G21: 1.2520146e+08
A22: Bebida | B22: 0.33003161 | F22: Norteamérica | G22: 27965990
A23: Snacks | B23: 0.36138419 | F23: Total general | G23: 1.2891019e+09
A24: Alimento infantil | B24: 0.37550924
A25: Cosméticos | B25: 0.39768984
A26: Verduras | B26: 0.40977541
A27: Cereales | B27: 0.43067574
A28: Ropa | B28: 0.67203514
A29: Total general | B29: 0.29635003

Sheet Dashboard_ Final
A1: LA AMALFITANA S.A.
B2: VENTA TOTAL | E2: COSTE TOTAL | H2: MARGEN DE VENTAS
B3: =Tablas_Dinamicas!P8 -> $ 1.289 M | E3: =Tablas_Dinamicas!P9 -> $ 907 M | H3: =Tablas_Dinamicas!P10 -> 29,6%
B5: =Tablas_Dinamicas!S8 -> ▼ Bajo la meta ($ 1.500 M) | E5: =Tablas_Dinamicas!S9 -> ▼ Dentro del máximo ($ 1.000 M) | H5: =Tablas_Dinamicas!S10 -> ▼ Bajo la meta (35,0%)
B44: CONCLUSIONES (datos sin filtros, 2020–2022)
B45: 1. Las ventas crecieron 10,5% en 2021 ($437 M → $483 M) y cayeron 23,7% en 2022 ($369 M). Ojo: los datos de 2022 llegan solo hasta el 7/11/2022, así que parte de la caída puede deberse a que el año está incompleto.
B46: 2. Las ventas están muy concentradas: África ($506 M, 39%) y Europa ($286 M, 22%) suman el 61% del total, mientras que Norteamérica aporta apenas el 2% ($28 M). Hay dependencia de dos regiones y una oportunidad de crecimiento en las más chicas.
B47: 3. El margen total (29,6%) no llega a la meta del 35%. La rentabilidad varía mucho por producto: Ropa deja 67% de margen, mientras que Cárnicos (13,6%) y Material de oficina (19,4%) son los que más bajan el promedio. Mejorar precios o costos en esos productos ayudaría a acercarse a la meta.
B49: REVISIÓN CRÍTICA (abogado del diablo con IA) – qué cambia en las conclusiones
B50: ="• Ventas: comparando el mismo período (1/1 al "&TEXT(Apoyo!C4,"dd/mm")&" de cada año), 2022 cayó "&TEXT(-Apoyo!E9,"0,0%")&" frente a 2021, y no "&TEXT(-Apoyo!G9,"0,0%")&". La caída es real, pero menor: una parte se debía a que 2022 está incompleto." -> • Ventas: comparando el mismo período (1/1 al 07/11 de cada año), 2022 cayó 14,6% frente a 2021, y no 23,7%. La caída es real, pero menor: una parte se debía a que 2022 está incompleto.
B51: ="• Productos: Ropa tiene el mayor margen ("&TEXT(Apoyo!F25,"0%")&"), pero aporta solo el "&TEXT(Apoyo!G25,"0,0%")&" de la ganancia. Los que más ganancia dejan son Doméstico ("&TEXT(Apoyo!G26,"0,0%")&") y Cosméticos ("&TEXT(Apoyo!G21,"0,0%")&"). Doméstico, Material de oficina y Cárnicos venden mucho con margen bajo: ahí está la mayor palanca para llegar al 35%." -> • Productos: Ropa tiene el mayor margen (67%), pero aporta solo el 7,3% de la ganancia. Los que más ganancia dejan son Doméstico (17,4%) y Cosméticos (16,9%). Doméstico, Material de oficina y Cárnicos venden mucho con margen bajo: ahí está la mayor palanca para llegar al 35%.
B52: ="• Regiones: la concentración en África y Europa es un riesgo a validar; falta analizar margen, clientes y evolución por región antes de concluir." -> • Regiones: la concentración en África y Europa es un riesgo a validar; falta analizar margen, clientes y evolución por región antes de concluir.

Sheet Apoyo
A1: ANÁLISIS DE APOYO – Revisión crítica (IA)
A3: 1. Ventas en períodos equivalentes (del 1/1 a la fecha del último pedido de cada año)
A4: Último pedido registrado | C4: =MAX(Hechos!$D$2:$D$1001) -> 44872
A6: Año | B6: Desde | C6: Hasta | D6: Ventas mismo período ($) | E6: Var. % vs año anterior | F6: Ventas año completo ($) | G6: Var. % año completo
A7: 2020 | B7: =DATE(VALUE(A7),1,1) -> 43831 | C7: =DATE(VALUE(A7),MONTH($C$4),DAY($C$4)) -> 44142 | D7: =SUMIFS(Hechos!$J$2:$J$1001,Hechos!$D$2:$D$1001,">="&B7,Hechos!$D$2:$D$1001,"<="&C7) -> 3.6061012e+08 | E7: - | F7: =SUMIFS(Hechos!$J$2:$J$1001,Hechos!$D$2:$D$1001,">="&B7,Hechos!$D$2:$D$1001,"<="&DATE(VALUE(A7),12,31)) -> 4.3729163e+08 | G7: -
A8: =TEXT(VALUE(A7)+1,"0") -> 2021 | B8: =DATE(VALUE(A8),1,1) -> 44197 | C8: =DATE(VALUE(A8),MONTH($C$4),DAY($C$4)) -> 44507 | D8: =SUMIFS(Hechos!$J$2:$J$1001,Hechos!$D$2:$D$1001,">="&B8,Hechos!$D$2:$D$1001,"<="&C8) -> 4.3145274e+08 | E8: =D8/D7-1 -> 0.1964521 | F8: =SUMIFS(Hechos!$J$2:$J$1001,Hechos!$D$2:$D$1001,">="&B8,Hechos!$D$2:$D$1001,"<="&DATE(VALUE(A8),12,31)) -> 4.832354e+08 | G8: =F8/F7-1 -> 0.10506436
A9: =TEXT(VALUE(A8)+1,"0") -> 2022 | B9: =DATE(VALUE(A9),1,1) -> 44562 | C9: =DATE(VALUE(A9),MONTH($C$4),DAY($C$4)) -> 44872 | D9: =SUMIFS(Hechos!$J$2:$J$1001,Hechos!$D$2:$D$1001,">="&B9,Hechos!$D$2:$D$1001,"<="&C9) -> 3.6857487e+08 | E9: =D9/D8-1 -> -0.14573523 | F9: =SUMIFS(Hechos!$J$2:$J$1001,Hechos!$D$2:$D$1001,">="&B9,Hechos!$D$2:$D$1001,"<="&DATE(VALUE(A9),12,31)) -> 3.6857487e+08 | G9: =F9/F8-1 -> -0.23727675
A10: Total | D10: =SUM(D7:D9) -> 1.1606377e+09 | F10: =SUM(F7:F9) -> 1.2891019e+09
A11: Control: total año completo = suma de la hoja Hechos | F11: =IF(ROUND(F10-SUM(Hechos!$J$2:$J$1001),0)=0,"OK","Revisar") -> OK
A13: 2. Venta, ganancia y margen por producto (total 2020–2022, sin filtros) | I13: Base del gráfico (ordenada por ganancia)
A14: Producto | B14: ID | C14: Ventas ($) | D14: Coste ($) | E14: Ganancia ($) | F14: Margen % | G14: % de la ganancia total | I14: Producto | J14: Ganancia ($) | K14: Margen %
A15: =Dim_Productos!B2 -> Snacks | B15: =Dim_Productos!A2 -> PRO 1 | C15: =SUMIFS(Hechos!$J$2:$J$1001,Hechos!$B$2:$B$1001,B15) -> 71156446 | D15: =SUMIFS(Hechos!$K$2:$K$1001,Hechos!$B$2:$B$1001,B15) -> 45441631 | E15: =C15-D15 -> 25714815 | F15: =IF(C15=0,0,E15/C15) -> 0.36138419 | G15: =E15/$E$27 -> 0.067311797 | I15: {=_xlfn.SORTBY(A15:A26,E15:E26,-1)} -> Doméstico | J15: {=_xlfn.SORTBY(E15:E26,E15:E26,-1)} -> 66660915 | K15: {=_xlfn.SORTBY(F15:F26,E15:E26,-1)} -> 0.24799856
A16: =Dim_Productos!B3 -> Cárnicos | B16: =Dim_Productos!A3 -> PRO 2 | C16: =SUMIFS(Hechos!$J$2:$J$1001,Hechos!$B$2:$B$1001,B16) -> 1.7852275e+08 | D16: =SUMIFS(Hechos!$K$2:$K$1001,Hechos!$B$2:$B$1001,B16) -> 1.5431857e+08 | E16: =C16-D16 -> 24204180 | F16: =IF(C16=0,0,E16/C16) -> 0.13558036 | G16: =E16/$E$27 -> 0.063357518 | I16: Cosméticos | J16: 64511334 | K16: 0.39768984
A17: =Dim_Productos!B4 -> Cereales | B17: =Dim_Productos!A4 -> PRO 3 | C17: =SUMIFS(Hechos!$J$2:$J$1001,Hechos!$B$2:$B$1001,B17) -> 93401170 | D17: =SUMIFS(Hechos!$K$2:$K$1001,Hechos!$B$2:$B$1001,B17) -> 53175552 | E17: =C17-D17 -> 40225618 | F17: =IF(C17=0,0,E17/C17) -> 0.43067574 | G17: =E17/$E$27 -> 0.10529567 | I17: Material de oficina | J17: 45996031 | K17: 0.19386987
A18: =Dim_Productos!B5 -> Frutas | B18: =Dim_Productos!A5 -> PRO 4 | C18: =SUMIFS(Hechos!$J$2:$J$1001,Hechos!$B$2:$B$1001,B18) -> 3820392.4 | D18: =SUMIFS(Hechos!$K$2:$K$1001,Hechos!$B$2:$B$1001,B18) -> 2833560.1 | E18: =C18-D18 -> 986832.34 | F18: =IF(C18=0,0,E18/C18) -> 0.25830654 | G18: =E18/$E$27 -> 0.0025831591 | I18: Alimento infantil | J18: 41386501 | K18: 0.37550924
A19: =Dim_Productos!B6 -> Alimento infantil | B19: =Dim_Productos!A6 -> PRO 5 | C19: =SUMIFS(Hechos!$J$2:$J$1001,Hechos!$B$2:$B$1001,B19) -> 1.1021433e+08 | D19: =SUMIFS(Hechos!$K$2:$K$1001,Hechos!$B$2:$B$1001,B19) -> 68827831 | E19: =C19-D19 -> 41386501 | F19: =IF(C19=0,0,E19/C19) -> 0.37550924 | G19: =E19/$E$27 -> 0.10833443 | I19: Cereales | J19: 40225618 | K19: 0.43067574
A20: =Dim_Productos!B7 -> Bebida | B20: =Dim_Productos!A7 -> PRO 6 | C20: =SUMIFS(Hechos!$J$2:$J$1001,Hechos!$B$2:$B$1001,B20) -> 21667948 | D20: =SUMIFS(Hechos!$K$2:$K$1001,Hechos!$B$2:$B$1001,B20) -> 14516840 | E20: =C20-D20 -> 7151107.7 | F20: =IF(C20=0,0,E20/C20) -> 0.33003161 | G20: =E20/$E$27 -> 0.018718934 | I20: Ropa | J20: 27712143 | K20: 0.67203514
A21: =Dim_Productos!B8 -> Cosméticos | B21: =Dim_Productos!A8 -> PRO 7 | C21: =SUMIFS(Hechos!$J$2:$J$1001,Hechos!$B$2:$B$1001,B21) -> 1.6221519e+08 | D21: =SUMIFS(Hechos!$K$2:$K$1001,Hechos!$B$2:$B$1001,B21) -> 97703857 | E21: =C21-D21 -> 64511334 | F21: =IF(C21=0,0,E21/C21) -> 0.39768984 | G21: =E21/$E$27 -> 0.16886662 | I21: Verduras | J21: 26069092 | K21: 0.40977541
A22: =Dim_Productos!B9 -> Cuidado personal | B22: =Dim_Productos!A9 -> PRO 8 | C22: =SUMIFS(Hechos!$J$2:$J$1001,Hechos!$B$2:$B$1001,B22) -> 37201861 | D22: =SUMIFS(Hechos!$K$2:$K$1001,Hechos!$B$2:$B$1001,B22) -> 25795051 | E22: =C22-D22 -> 11406811 | F22: =IF(C22=0,0,E22/C22) -> 0.30661936 | G22: =E22/$E$27 -> 0.029858777 | I22: Snacks | J22: 25714815 | K22: 0.36138419
A23: =Dim_Productos!B10 -> Material de oficina | B23: =Dim_Productos!A10 -> PRO 9 | C23: =SUMIFS(Hechos!$J$2:$J$1001,Hechos!$B$2:$B$1001,B23) -> 2.3725208e+08 | D23: =SUMIFS(Hechos!$K$2:$K$1001,Hechos!$B$2:$B$1001,B23) -> 1.9125605e+08 | E23: =C23-D23 -> 45996031 | F23: =IF(C23=0,0,E23/C23) -> 0.19386987 | G23: =E23/$E$27 -> 0.12040046 | I23: Cárnicos | J23: 24204180 | K23: 0.13558036
A24: =Dim_Productos!B11 -> Verduras | B24: =Dim_Productos!A11 -> PRO 10 | C24: =SUMIFS(Hechos!$J$2:$J$1001,Hechos!$B$2:$B$1001,B24) -> 63617999 | D24: =SUMIFS(Hechos!$K$2:$K$1001,Hechos!$B$2:$B$1001,B24) -> 37548907 | E24: =C24-D24 -> 26069092 | F24: =IF(C24=0,0,E24/C24) -> 0.40977541 | G24: =E24/$E$27 -> 0.068239162 | I24: Cuidado personal | J24: 11406811 | K24: 0.30661936
A25: =Dim_Productos!B12 -> Ropa | B25: =Dim_Productos!A12 -> PRO 11 | C25: =SUMIFS(Hechos!$J$2:$J$1001,Hechos!$B$2:$B$1001,B25) -> 41236152 | D25: =SUMIFS(Hechos!$K$2:$K$1001,Hechos!$B$2:$B$1001,B25) -> 13524009 | E25: =C25-D25 -> 27712143 | F25: =IF(C25=0,0,E25/C25) -> 0.67203514 | G25: =E25/$E$27 -> 0.072540058 | I25: Bebida | J25: 7151107.7 | K25: 0.33003161
A26: =Dim_Productos!B13 -> Doméstico | B26: =Dim_Productos!A13 -> PRO 12 | C26: =SUMIFS(Hechos!$J$2:$J$1001,Hechos!$B$2:$B$1001,B26) -> 2.6879557e+08 | D26: =SUMIFS(Hechos!$K$2:$K$1001,Hechos!$B$2:$B$1001,B26) -> 2.0213465e+08 | E26: =C26-D26 -> 66660915 | F26: =IF(C26=0,0,E26/C26) -> 0.24799856 | G26: =E26/$E$27 -> 0.17449342 | I26: Frutas | J26: 986832.34 | K26: 0.25830654
A27: Total | C27: =SUM(C15:C26) -> 1.2891019e+09 | D27: =SUM(D15:D26) -> 9.0707652e+08 | E27: =C27-D27 -> 3.8202538e+08 | F27: =E27/C27 -> 0.29635003 | G27: =SUM(G15:G26) -> 1
